CHANGELOG.txt
LICENSE.rst
MANIFEST.in
README.rst
requirements.txt
setup.cfg
setup.py
ReOBJ/MainCode.py
ReOBJ/ProjectErr.py
ReOBJ/Version.py
ReOBJ/__init__.py
ReOBJ.egg-info/PKG-INFO
ReOBJ.egg-info/SOURCES.txt
ReOBJ.egg-info/dependency_links.txt
ReOBJ.egg-info/requires.txt
ReOBJ.egg-info/top_level.txt
ReOBJ.egg-info/zip-safe
ReOBJ/__pycache__/Version.cpython-34.pyc
ReOBJ/__pycache__/__init__.cpython-34.pyc