Metadata-Version: 1.1
Name: ReOBJ
Version: 1.1.0
Summary: R(estricted) E(xtended) Objects. Simple, reasonable fast, restricted/extended python objects.
Home-page: https://github.com/peter1000/
Author: peter1000
Author-email: https://github.com/peter1000
License: BSD-3-Clause
Keywords: python dictionary mapping hash table list matrix
Platform: Linux
Classifier: Development Status :: 3 - Alpha
Classifier: Operating System :: POSIX :: Linux
Classifier: Programming Language :: Python :: 3
Classifier: Topic :: Software Development
Classifier: Topic :: Software Development :: Libraries :: Python Modules
